odoo/addons/account_journal_lock_date/README.rst
odoo/addons/account_journal_lock_date/__init__.py
odoo/addons/account_journal_lock_date/__manifest__.py
odoo/addons/account_journal_lock_date/i18n/account_journal_lock_date.pot
odoo/addons/account_journal_lock_date/i18n/am.po
odoo/addons/account_journal_lock_date/i18n/ar.po
odoo/addons/account_journal_lock_date/i18n/bs.po
odoo/addons/account_journal_lock_date/i18n/ca.po
odoo/addons/account_journal_lock_date/i18n/cs.po
odoo/addons/account_journal_lock_date/i18n/de.po
odoo/addons/account_journal_lock_date/i18n/en_GB.po
odoo/addons/account_journal_lock_date/i18n/es.po
odoo/addons/account_journal_lock_date/i18n/es_CR.po
odoo/addons/account_journal_lock_date/i18n/es_EC.po
odoo/addons/account_journal_lock_date/i18n/es_MX.po
odoo/addons/account_journal_lock_date/i18n/es_VE.po
odoo/addons/account_journal_lock_date/i18n/et.po
odoo/addons/account_journal_lock_date/i18n/fr.po
odoo/addons/account_journal_lock_date/i18n/gl.po
odoo/addons/account_journal_lock_date/i18n/hr.po
odoo/addons/account_journal_lock_date/i18n/hr_HR.po
odoo/addons/account_journal_lock_date/i18n/hu.po
odoo/addons/account_journal_lock_date/i18n/id.po
odoo/addons/account_journal_lock_date/i18n/it.po
odoo/addons/account_journal_lock_date/i18n/ja.po
odoo/addons/account_journal_lock_date/i18n/lt.po
odoo/addons/account_journal_lock_date/i18n/mk.po
odoo/addons/account_journal_lock_date/i18n/mn.po
odoo/addons/account_journal_lock_date/i18n/nb.po
odoo/addons/account_journal_lock_date/i18n/nl.po
odoo/addons/account_journal_lock_date/i18n/nl_BE.po
odoo/addons/account_journal_lock_date/i18n/pl.po
odoo/addons/account_journal_lock_date/i18n/pt.po
odoo/addons/account_journal_lock_date/i18n/pt_BR.po
odoo/addons/account_journal_lock_date/i18n/pt_PT.po
odoo/addons/account_journal_lock_date/i18n/ro.po
odoo/addons/account_journal_lock_date/i18n/ru.po
odoo/addons/account_journal_lock_date/i18n/sl.po
odoo/addons/account_journal_lock_date/i18n/sr@latin.po
odoo_addon_account_journal_lock_date-18.0.1.0.0.4.dist-info/METADATA
odoo_addon_account_journal_lock_date-18.0.1.0.0.4.dist-info/WHEEL
odoo_addon_account_journal_lock_date-18.0.1.0.0.4.dist-info/top_level.txt
odoo_addon_account_journal_lock_date-18.0.1.0.0.4.dist-info/RECORD
